Metadata-Version: 1.1
Name: content-insights-statsd
Version: 0.13.0
Summary: A test module for statsd in airflow operator
Home-page: UNKNOWN
Author: myang
Author-email: 407768752@qq.com
License: Apache License, Version 2.0
Platform: linux/Windows
Classifier: Development Status :: 3 - Alpha
Classifier: Topic :: Text Processing
Classifier: License :: OSI Approved :: MIT License
Classifier: Programming Language :: Python :: 2
Classifier: Programming Language :: Python :: 2.7
Classifier: Programming Language :: Python :: 3
Classifier: Programming Language :: Python :: 3.5
